dictionary/__init__.py
dictionary/dictionary.py
very_simple_dictionary_ece_unal-2.0.0.dist-info/METADATA
very_simple_dictionary_ece_unal-2.0.0.dist-info/WHEEL
very_simple_dictionary_ece_unal-2.0.0.dist-info/top_level.txt
very_simple_dictionary_ece_unal-2.0.0.dist-info/RECORD
